LICENSE.rst
MANIFEST.in
README.rst
setup.cfg
setup.py
dtool_create/__init__.py
dtool_create/dataset.py
dtool_create/publish.py
dtool_create/utils.py
dtool_create.egg-info/PKG-INFO
dtool_create.egg-info/SOURCES.txt
dtool_create.egg-info/dependency_links.txt
dtool_create.egg-info/entry_points.txt
dtool_create.egg-info/requires.txt
dtool_create.egg-info/top_level.txt
dtool_create/templates/README.yml