Metadata-Version: 1.1
Name: dtool-create
Version: 0.23.4
Summary: Dtool plugin for creating datasets
Home-page: https://github.com/jic-dtool/dtool-create
Author: Tjelvar Olsson
Author-email: tjelvar.olsson@gmail.com
License: MIT
Download-URL: https://github.com/jic-dtool/dtool-create/tarball/0.23.4
Platform: UNKNOWN
